bohrium/__init__.py
bohrium/_base_client.py
bohrium/_client.py
bohrium/_constants.py
bohrium/_exceptions.py
bohrium/_resource.py
bohrium/_response.py
bohrium/_types.py
bohrium/_version.py
bohrium/_utils/__init__.py
bohrium/_utils/_logs.py
bohrium/_utils/_typing.py
bohrium/_utils/_utils.py
bohrium/resources/__init__.py
bohrium/resources/job/__init__.py
bohrium/resources/job/job.py
bohrium/resources/tiefblue/__init__.py
bohrium/resources/tiefblue/tiefblue.py
bohrium/types/__init__.py
bohrium/types/job/__init__.py
bohrium/types/job/job.py
bohrium_sdk-0.14.0.dist-info/METADATA
bohrium_sdk-0.14.0.dist-info/WHEEL
bohrium_sdk-0.14.0.dist-info/top_level.txt
bohrium_sdk-0.14.0.dist-info/RECORD
