Metadata-Version: 2.1
Name: bohrium-sdk
Version: 0.14.0
Summary: bohrium openapi python sdk
Home-page: https://github.com/dingzhaohan
Author: dingzhaohan
Author-email: dingzh@dp.tech
Requires-Python: >=3.7
Requires-Dist: distro
Requires-Dist: httpx
Requires-Dist: typing-extensions
Requires-Dist: anyio
Requires-Dist: pyhumps
Requires-Dist: requests
Requires-Dist: tqdm
